triton/__init__.py
triton_xpu-0.0.2.dist-info/METADATA
triton_xpu-0.0.2.dist-info/WHEEL
triton_xpu-0.0.2.dist-info/top_level.txt
triton_xpu-0.0.2.dist-info/RECORD
